perhaps/__init__.py
perhaps/maybe.py
perhaps-0.5.4.dist-info/LICENSE
perhaps-0.5.4.dist-info/METADATA
perhaps-0.5.4.dist-info/WHEEL
perhaps-0.5.4.dist-info/RECORD
