Metadata-Version: 2.1
Name: perhaps
Version: 0.5.4
Summary: Perhaps there is no data or perhaps there is
Home-page: https://github.com/HKGx/perhaps
License: MIT
Keywords: maybe,monad,functional programming,just,some
Author: HKGx
Author-email: mail@hkgdoes.dev
Requires-Python: >=3.12,<4.0
Classifier: Development Status :: 3 - Alpha
Classifier: License :: OSI Approved :: MIT License
Classifier: Programming Language :: Python :: 3
Classifier: Programming Language :: Python :: 3.12
Classifier: Topic :: Software Development :: Libraries :: Python Modules
Project-URL: Repository, https://github.com/HKGx/perhaps
